mantaray_py/__init__.py
mantaray_py/__version__.py
mantaray_py/node.py
mantaray_py/py.typed
mantaray_py/utils.py
mantaray_py/types/__init__.py
mantaray_py/types/get_random_values.py
mantaray_py/types/types.py
mantaray_py-0.0.1.dist-info/METADATA
mantaray_py-0.0.1.dist-info/WHEEL
mantaray_py-0.0.1.dist-info/licenses/AUTHORS.md
mantaray_py-0.0.1.dist-info/licenses/LICENSE
mantaray_py-0.0.1.dist-info/RECORD
