Metadata-Version: 2.3
Name: mantaray-py
Version: 0.0.1
Summary: Mantaray data structure in Python
Project-URL: Documentation, https://ankvik-tech-labs.github.io/mantaray-py/
Project-URL: Source, https://github.com/Ankvik-Tech-Labs/mantaray-py
Author-email: mantaray-py <github.maturity983@passinbox.com>
License: BSD 3-Clause License
License-File: AUTHORS.md
License-File: LICENSE
Classifier: Programming Language :: Python :: 3
Classifier: Programming Language :: Python :: 3.9
Classifier: Programming Language :: Python :: 3.10
Classifier: Programming Language :: Python :: 3.11
Classifier: Programming Language :: Python :: 3.12
Classifier: Programming Language :: Python :: Implementation :: CPython
Classifier: Programming Language :: Python :: Implementation :: PyPy
Requires-Python: >=3.9
